[
  {
    "date": "2026-04-16_21-47-47",
    "folder": "2026-04-16_21-47-47",
    "failed": 4,
    "passed": 254,
    "total": 258,
    "success": 98.45
  },
  {
    "date": "2026-04-16_21-50-53",
    "folder": "2026-04-16_21-50-53",
    "failed": 4,
    "passed": 254,
    "total": 258,
    "success": 98.45
  },
  {
    "date": "2026-04-16_21-54-18",
    "folder": "2026-04-16_21-54-18",
    "failed": 4,
    "passed": 254,
    "total": 258,
    "success": 98.45
  },
  {
    "date": "2026-04-17_11-18-36",
    "folder": "2026-04-17_11-18-36",
    "failed": 5,
    "passed": 253,
    "total": 258,
    "success": 98.06
  },
  {
    "date": "2026-04-17_12-03-19",
    "folder": "2026-04-17_12-03-19",
    "failed": 4,
    "passed": 254,
    "total": 258,
    "success": 98.45,
    "summary": {
      "requests": 62,
      "prerequest": 61,
      "tests": 61
    }
  },
  {
    "date": "2026-04-17_13-00-07",
    "folder": "2026-04-17_13-00-07",
    "failed": 4,
    "passed": 254,
    "total": 258,
    "success": 98.45,
    "summary": {
      "requests": 62,
      "prerequest": 61,
      "tests": 61
    }
  },
  {
    "date": "2026-04-17_10-32-11",
    "folder": "2026-04-17_10-32-11",
    "failed": 4,
    "passed": 254,
    "total": 258,
    "success": 98.45,
    "summary": {
      "requests": 62,
      "prerequest": 61,
      "tests": 61
    }
  },
  {
    "date": "2026-04-17_10-38-43",
    "folder": "2026-04-17_10-38-43",
    "failed": 4,
    "passed": 254,
    "total": 258,
    "success": 98.45,
    "summary": {
      "requests": 62,
      "prerequest": 61,
      "tests": 61
    }
  }
]
